{
    "title": "[F1] Arriving in style in Monaco",
    "comments": [
        {
            "depth": 0,
            "author": "poopellar",
            "body": "Hulk Nukem ready to set pole in a wet quali and finish 4th on Sunday.",
            "score": 1,
            "replies": [
                {
                    "depth": 1,
                    "author": "CoachRyanWalters",
                    "body": "Why not make it more devastating? Third across the line but 10 second penalty while the race finishes under a SC?",
                    "score": 1,
                    "replies": [
                        {
                            "depth": 2,
                            "author": "MightySDS",
                            "body": "Damn, calm down Satan.",
                            "score": 1
                        }
                    ]
                },
                {
                    "depth": 1,
                    "author": "Bhenny_5",
                    "body": "Race 'em baby!!",
                    "score": 1
                },
                {
                    "depth": 1,
                    "author": "bafila",
                    "body": "\u201cI\u2019m here to get pole and chew bubblegum, and I\u2019m all out of bubblegum\u201d",
                    "score": 1
                },
                {
                    "depth": 1,
                    "author": "emolano",
                    "body": "It has been said",
                    "score": 1
                }
            ]
        },
        {
            "depth": 0,
            "author": "nn4260029",
            "body": "Absent: Max, who\u2019s probably wearing skinny jeans and either a white Alpha Tauri shirt or a plastic RBR sponsor shirt.",
            "score": 1,
            "replies": [
                {
                    "depth": 1,
                    "author": "shitrod",
                    "body": "Max is too busy on the sim to go outside",
                    "score": 1
                },
                {
                    "depth": 1,
                    "author": "stancesantos_yt",
                    "body": "he\u2019s definitely wearing his red bull team wear. Dude practically lives in it",
                    "score": 1
                }
            ]
        },
        {
            "depth": 0,
            "author": "freshicedmatchalatte",
            "body": "People usually talk about Lewis or Zhou outfits, yet IMO Hulk has always looked like a movie actor attending his movie's premiere.",
            "score": 1,
            "replies": [
                {
                    "depth": 1,
                    "author": "jauhesammutin_",
                    "body": "He looks like the main henchman in a James Bond movie in this pic.",
                    "score": 1
                },
                {
                    "depth": 1,
                    "author": "Mother-Fucking-Cunt",
                    "body": "I think that\u2019s because Hamiltons and Zhou wear the kind of outfits you\u2019d see in a fashion show but most would never wear whilst Hulk wears pretty simple clothes but just looks good naturally",
                    "score": 1,
                    "replies": [
                        {
                            "depth": 2,
                            "author": "freshicedmatchalatte",
                            "body": "Good point. Yeah, Hulk always dresses up and looks dashing; wears outfits people normally wear on a regular basis.",
                            "score": 1
                        },
                        {
                            "depth": 2,
                            "author": "Rivendel93",
                            "body": "I'd wear Lewis's sweater if I looked like Lewis in it lol, actually a cool looking material.",
                            "score": 1
                        }
                    ]
                },
                {
                    "depth": 1,
                    "author": "scobydoby",
                    "body": "Hulk doesn\u2019t have particularly strong fashion, he\u2019s just very attractive.",
                    "score": 1
                },
                {
                    "depth": 1,
                    "author": "fuckhandsmcmikee",
                    "body": "No one talks about hulks outfits because the dude has absolutely zero style lmao",
                    "score": 1
                }
            ]
        },
        {
            "depth": 0,
            "author": "NorthKoreanMissile7",
            "body": "Hulk looks like James Bond's sexy german cousin.",
            "score": 1,
            "replies": [
                {
                    "depth": 1,
                    "author": "hkrb1999",
                    "body": "00(2)7",
                    "score": 1
                },
                {
                    "depth": 1,
                    "author": "stancesantos_yt",
                    "body": "The names Hulk. Huuuuulkenburg",
                    "score": 1
                }
            ]
        },
        {
            "depth": 0,
            "author": "Cobretti18",
            "body": "I would\u2019ve loved to have been an F1 driver\u2026 could\u2019ve amassed an incredible collection of free sunglasses",
            "score": 1,
            "replies": [
                {
                    "depth": 1,
                    "author": "pancoste",
                    "body": "...*and get paid to wear them in public.",
                    "score": 1
                }
            ]
        },
        {
            "depth": 0,
            "author": "SnooCakes9525",
            "body": "Hulk and Logan gotta be my favorites with how they rock those shades... meanwhile the VCARB drivers have ascended to a new level of drip that surpasses shades altogether",
            "score": 1
        },
        {
            "depth": 0,
            "author": "ashyjay",
            "body": "Daddy Hulk has it going on with that smoulder.",
            "score": 1
        },
        {
            "depth": 0,
            "author": "MrMarbles77",
            "body": "Yuki's looking like my memories of trying on hand-me-down clothes, \"It's great, you'll grow into it.\"",
            "score": 1,
            "replies": [
                {
                    "depth": 1,
                    "author": "TrickiestToast",
                    "body": "Must be a hand me down from stroll",
                    "score": 1,
                    "replies": [
                        {
                            "depth": 2,
                            "author": "DadWagonDriver",
                            "body": "That is a fantastically subtle joke lol.",
                            "score": 1
                        }
                    ]
                },
                {
                    "depth": 1,
                    "author": "AOCMarryMe",
                    "body": "Yuki needs a stylist",
                    "score": 1
                }
            ]
        },
        {
            "depth": 0,
            "author": "m0nkeyhero",
            "body": "Hulk is all out of bubblegum",
            "score": 1
        },
        {
            "depth": 0,
            "author": "WiSoSirius",
            "body": "They don't just come downstairs in pajamas, circle it up, and walk back up to bed?",
            "score": 1,
            "replies": [
                {
                    "depth": 1,
                    "author": "PradaAndPunishment",
                    "body": "Pierre and Esteban casually walking across the border also",
                    "score": 1
                }
            ]
        },
        {
            "depth": 0,
            "author": "Peanutspitter96",
            "body": "Next 007 villain",
            "score": 1
        },
        {
            "depth": 0,
            "author": "Extravagod",
            "body": "Hulk looks friggin cool.",
            "score": 1
        },
        {
            "depth": 0,
            "author": "TonyLannister",
            "body": "Hulk is hurting them with those Prada shades",
            "score": 1
        },
        {
            "depth": 0,
            "author": "shdwflyr",
            "body": "Hulk looking even more gorgeous than Charles.",
            "score": 1
        },
        {
            "depth": 0,
            "author": "PsychoDye",
            "body": "Got my upvote for the Williams pic transition.",
            "score": 1
        },
        {
            "depth": 0,
            "author": "BountyLaws",
            "body": "Ricciardo looking even more Australian",
            "score": 1
        },
        {
            "depth": 0,
            "author": "mattscott53",
            "body": "lewis always looks like his fashion inspiration is the movie zoolander",
            "score": 1
        },
        {
            "depth": 0,
            "author": "realgamergirlTM",
            "body": "My dream for 2025 is that Lewis teaches Charles how to dress",
            "score": 1,
            "replies": [
                {
                    "depth": 1,
                    "author": "Imaginary-Buddy5186",
                    "body": "It would be better if Charles teaches Lewis",
                    "score": 1
                },
                {
                    "depth": 1,
                    "author": "TheEmuWar_",
                    "body": "Like a fucking tosser?",
                    "score": 1,
                    "replies": [
                        {
                            "depth": 2,
                            "author": "TheRedWire123",
                            "body": "Who hurt you?",
                            "score": 1
                        }
                    ]
                }
            ]
        },
        {
            "depth": 0,
            "author": "whimsical_trash",
            "body": "Is Danny not wearing pants?",
            "score": 1,
            "replies": [
                {
                    "depth": 1,
                    "author": "REO_Jerkwagon",
                    "body": "That stood out to me as well.  I see the ink on his leg... he's either got on no pants at all, or the shortest shorts he could find.",
                    "score": 1,
                    "replies": [
                        {
                            "depth": 2,
                            "author": "whimsical_trash",
                            "body": "Or I was thinking some tight, weird tattoo design shorts but doesn't really seem his style lol",
                            "score": 1
                        }
                    ]
                }
            ]
        },
        {
            "depth": 0,
            "author": "MakingYouMad",
            "body": "Yuki always looks dripped out",
            "score": 1,
            "replies": [
                {
                    "depth": 1,
                    "author": "teachd12",
                    "body": "For real",
                    "score": 1
                }
            ]
        },
        {
            "depth": 0,
            "author": "MyCarHasTwoHorns",
            "body": "Thought Danny was wearing a Dickies shirt for a second\n\nAnd Pierre, buddy, I love you. But it\u2019s time to book that budget flight to Turkey my friend.",
            "score": 1,
            "replies": [
                {
                    "depth": 1,
                    "author": "sleepingjiva",
                    "body": "Nah, we need bald-guy representation on the grid again, it's been years",
                    "score": 1
                },
                {
                    "depth": 1,
                    "author": "Middle_Emu_240",
                    "body": "Context?",
                    "score": 1,
                    "replies": [
                        {
                            "depth": 2,
                            "author": "possums101",
                            "body": "Turkey is the male hair transplant capital of the world",
                            "score": 1
                        },
                        {
                            "depth": 2,
                            "author": "MyCarHasTwoHorns",
                            "body": "Gasly wears a wig. Turkey is where people get hair transplants done on the cheap these days. Scores of stories about return flights from Istanbul where every dude has bandages wrapping their head.",
                            "score": 1,
                            "replies": [
                                {
                                    "depth": 3,
                                    "author": "Rivendel93",
                                    "body": "Gasly wears a wig? I feel like he has a receding hairline but a wig?",
                                    "score": 1
                                }
                            ]
                        }
                    ]
                },
                {
                    "depth": 1,
                    "author": "Winstonwill8",
                    "body": "Did you see that tweet showing Seb, Lewis and Gasly's hairlines in the rain at Imola run for Senna? \ud83e\udee3\ud83e\udee3",
                    "score": 1
                }
            ]
        },
        {
            "depth": 0,
            "author": "PM_ME_UR_DADS_COCK",
            "body": "Anyone got an ID on Albons shirt?",
            "score": 1,
            "replies": [
                {
                    "depth": 1,
                    "author": "PradaAndPunishment",
                    "body": "His own, Albon Athletics",
                    "score": 1
                }
            ]
        },
        {
            "depth": 0,
            "author": "cepxico",
            "body": "I think my favorite thing about high fashion is that looking like a toddler in clothes 3x your size is a good look lmao. \n\nTsunoda looks like how my mom dressed me in the 90s",
            "score": 1
        },
        {
            "depth": 0,
            "author": "spiral_out46N2",
            "body": "Anyone know what glasses PG is wearing?  Those are dope AF.",
            "score": 1,
            "replies": [
                {
                    "depth": 1,
                    "author": "PradaAndPunishment",
                    "body": "Giorgio Armani AR8184U in black",
                    "score": 1,
                    "replies": [
                        {
                            "depth": 2,
                            "author": "spiral_out46N2",
                            "body": "Thanks bud!!",
                            "score": 1
                        }
                    ]
                }
            ]
        },
        {
            "depth": 0,
            "author": "Cptn_haze",
            "body": "Aside from Hulk, who dressed these dudes?",
            "score": 1,
            "replies": [
                {
                    "depth": 1,
                    "author": "PradaAndPunishment",
                    "body": "They live two minutes away from where the paddock is, I wouldn't dress up fresh after a nap just for media fay either",
                    "score": 1
                }
            ]
        },
        {
            "depth": 0,
            "author": "pcguy951",
            "body": "ID on Ricciardo shirt?",
            "score": 1,
            "replies": [
                {
                    "depth": 1,
                    "author": "PradaAndPunishment",
                    "body": "It's Danny's [own shirt](https://enchante.co/products/indigo-stripe-shirt). Alex is wearing his own design too.",
                    "score": 1
                }
            ]
        },
        {
            "depth": 0,
            "author": "elodie_pdf",
            "body": "Daniel\u2019s neck gets thicker by the hour",
            "score": 1
        },
        {
            "depth": 0,
            "author": "SimRacing313",
            "body": "Hulk looking like an extra from a terminator movie",
            "score": 1
        },
        {
            "depth": 0,
            "author": "Specific-Ad-8430",
            "body": "Genuine question: Louis how in the fuck are you wearing a cashmere sweater in like 90F heat",
            "score": 1,
            "replies": [
                {
                    "depth": 1,
                    "author": "CandidLiterature",
                    "body": "I imagine it\u2019s cooler than the fireproof boiler suit so\u2026",
                    "score": 1,
                    "replies": [
                        {
                            "depth": 2,
                            "author": "Specific-Ad-8430",
                            "body": "Honestly, they're probably just used to dressing for fashion and not dressing for the weather like 95% of everyone else is.",
                            "score": 1,
                            "replies": [
                                {
                                    "depth": 3,
                                    "author": "CandidLiterature",
                                    "body": "It\u2019s honestly probably not that hot. I have loose knit clothes that are pretty good at keeping you cool or warm. It looks like it would be cooler than being topless.",
                                    "score": 1
                                }
                            ]
                        }
                    ]
                },
                {
                    "depth": 1,
                    "author": "RUNELORD_",
                    "body": "Bro is practically topless, what are you on about",
                    "score": 1
                }
            ]
        },
        {
            "depth": 0,
            "author": "outm",
            "body": "RB paying so low to their drivers that they can\u2019t afford a pair of sunglasses\u2026 SMH",
            "score": 1
        },
        {
            "depth": 0,
            "author": "roknir",
            "body": "1 if by land\n\n\n2 if by sea",
            "score": 1,
            "replies": [
                {
                    "depth": 1,
                    "author": "Aken42",
                    "body": "Looks like George is number 2.",
                    "score": 1,
                    "replies": [
                        {
                            "depth": 2,
                            "author": "roknir",
                            "body": "always has been a solid #2",
                            "score": 1,
                            "replies": [
                                {
                                    "depth": 3,
                                    "author": "Aken42",
                                    "body": "Definitely a Bristol #4.",
                                    "score": 1,
                                    "replies": [
                                        {
                                            "depth": 4,
                                            "author": "roknir",
                                            "body": "is that what they call \ud83d\udca9 in Bristol?",
                                            "score": 1
                                        }
                                    ]
                                }
                            ]
                        }
                    ]
                }
            ]
        },
        {
            "depth": 0,
            "author": "EUblij",
            "body": "Looks like your criminal cousin, headed for court.",
            "score": 1
        },
        {
            "depth": 0,
            "author": "Bourbonaddicted",
            "body": "Well half of them arriving from home",
            "score": 1
        },
        {
            "depth": 0,
            "author": "mtglilianavess",
            "body": "Danny with his new dickies shirt from Surf Dive N' Ski his dad bought him for his birthday.",
            "score": 1
        },
        {
            "depth": 0,
            "author": "Illywhatsthedilly",
            "body": "Yuki is Christian?",
            "score": 1
        },
        {
            "depth": 0,
            "author": "Reno117",
            "body": "Riccardo looking like that uncle who isn't allowed to be alone with the kids",
            "score": 1
        },
        {
            "depth": 0,
            "author": "6637733885362995955",
            "body": "Is RIC turning into Ian Fidance?",
            "score": 1
        },
        {
            "depth": 0,
            "author": "IkeaKarma",
            "body": "Ricciardo looks like he\u2019s got a hench bbq",
            "score": 1
        },
        {
            "depth": 0,
            "author": "Suknator",
            "body": "Logan looks sad",
            "score": 1,
            "replies": [
                {
                    "depth": 1,
                    "author": "PradaAndPunishment",
                    "body": "He looks so defeated. I feel bad for him",
                    "score": 1
                }
            ]
        },
        {
            "depth": 0,
            "author": "OddFirefighter3",
            "body": "Where is Max in his redbull tshirt",
            "score": 1
        },
        {
            "depth": 0,
            "author": "man_u_is_my_team",
            "body": "Logan looks like he\u2019s just been told Yuki is being interviewed this weekend and Danny\u2019s hair line is receding as quick as his career,",
            "score": 1,
            "replies": [
                {
                    "depth": 1,
                    "author": "PradaAndPunishment",
                    "body": "lmfao",
                    "score": 1
                }
            ]
        },
        {
            "depth": 0,
            "author": "Breaking-Dad-",
            "body": "Did some steal Gasly\u2019s coffee?",
            "score": 1
        },
        {
            "depth": 0,
            "author": "-crackhousebob",
            "body": "Half of them live in penthouses in Monaco during the off-season so they literally get out of bed, take the elevator down, and walk over to the race \ud83d\ude02\ud83d\ude02",
            "score": 1
        },
        {
            "depth": 0,
            "author": "MexicanRadio",
            "body": "I want Albons shirt.",
            "score": 1,
            "replies": [
                {
                    "depth": 1,
                    "author": "PradaAndPunishment",
                    "body": "He [just dropped it](https://www.alexalbon.com/shop/products/alex-albon-athletics-linen-button-up) for sale today!",
                    "score": 1
                }
            ]
        },
        {
            "depth": 0,
            "author": "air_max77",
            "body": "No pictures of Verstappen, we all know he's wearing RB merch. Same picture every Grand Prix.",
            "score": 1
        },
        {
            "depth": 0,
            "author": "drzrealest",
            "body": "Man, gasly has the best comb overs I've ever seen. His hair dresser is good",
            "score": 1
        },
        {
            "depth": 0,
            "author": "coconutpete52",
            "body": "Ocon still looking the Frenchest I have ever seen. Ricciardo somehow looks like he just left his job as a mechanic at Jiffy Lube in a suburb of Birmingham, Alabama.",
            "score": 1
        },
        {
            "depth": 0,
            "author": "MrTommy2",
            "body": "Hamilton has a knack for dressing like a total cooker and pulling it off every single time. Dude is so comfortable in his own skin",
            "score": 1
        },
        {
            "depth": 0,
            "author": "SAHE1986",
            "body": "Hamilton has no style. Hulk ftw.",
            "score": 1
        }
    ]
}